qualidator/__init__.py
qualidator/cli.py
qualidator/validations_registry.py
qualidator/connectors/__init__.py
qualidator/connectors/databricks.py
qualidator/inspectors/__init__.py
qualidator/inspectors/numeric.py
qualidator/inspectors/uniq.py
qualidator-0.3.0.dist-info/METADATA
qualidator-0.3.0.dist-info/WHEEL
qualidator-0.3.0.dist-info/entry_points.txt
qualidator-0.3.0.dist-info/top_level.txt
qualidator-0.3.0.dist-info/RECORD
